Jzdj/__init__.py
Jzdj/data_handler.py
Jzdj/gui.py
Jzdj/map_display.py
Jzdj-0.1.dist-info/METADATA
Jzdj-0.1.dist-info/WHEEL
Jzdj-0.1.dist-info/entry_points.txt
Jzdj-0.1.dist-info/top_level.txt
Jzdj-0.1.dist-info/RECORD
